<?xml version='1.1' encoding='UTF-8'?>
<com.cloudbees.plugins.credentials.SystemCredentialsProvider plugin="credentials@1311.vcf0a_900b_37c2">
  <domainCredentialsMap class="hudson.util.CopyOnWriteMap$Hash">
    <entry>
      <com.cloudbees.plugins.credentials.domains.Domain>
        <specifications/>
      </com.cloudbees.plugins.credentials.domains.Domain>
      <java.util.concurrent.CopyOnWriteArrayList>
        <com.cloudbees.plugins.credentials.impl.UsernamePasswordCredentialsImpl>
          <scope>GLOBAL</scope>
          <id>GitHub</id>
          <description>GitHub root token which has all permisssion for saikirangude account.</description>
          <username>saikirangude</username>
          <password>{AQAAABAAAAAwLBQ7HkfKwCPPxFt3QmuwfYHCGU5SdYfufvKIWjgPbmddLq+scuUt3M7Vi2Kyhk5Fh8ZY76DRv+M1v68zVDR9Kg==}</password>
          <usernameSecret>false</usernameSecret>
        </com.cloudbees.plugins.credentials.impl.UsernamePasswordCredentialsImpl>
        <org.jenkinsci.plugins.plaincredentials.impl.StringCredentialsImpl plugin="plain-credentials@143.v1b_df8b_d3b_e48">
          <scope>GLOBAL</scope>
          <id>SonarQube</id>
          <description>SonarQube-  this is the root token for accessing the sonar cloud server</description>
          <secret>{AQAAABAAAAAwh6Sls2e91JwCPUIMTY8CzvbiXVL6fkuxQY6lQDlAk52vjW8/4xlkD8JT032sh6ZjDjhRPcvZXgnOCXdXl6TYiA==}</secret>
        </org.jenkinsci.plugins.plaincredentials.impl.StringCredentialsImpl>
      </java.util.concurrent.CopyOnWriteArrayList>
    </entry>
  </domainCredentialsMap>
</com.cloudbees.plugins.credentials.SystemCredentialsProvider>